unbeheader/__init__.py
unbeheader/cli.py
unbeheader/config.py
unbeheader/headers.py
unbeheader/py.typed
unbeheader/typing.py
unbeheader/util.py
unbeheader-1.3.0.dist-info/LICENSE
unbeheader-1.3.0.dist-info/METADATA
unbeheader-1.3.0.dist-info/WHEEL
unbeheader-1.3.0.dist-info/entry_points.txt
unbeheader-1.3.0.dist-info/RECORD
