Metadata-Version: 2.1
Name: unbeheader
Version: 1.3.0
Summary: Never fail to maintain your file headers
Home-page: https://github.com/unconventionaldotdev/unbeheader
License: MIT
Author: Adrian Moennich
Author-email: adrian.moennich@cern.ch
Maintainer: Alejandro Avilés
Maintainer-email: ome@unconventional.dev
Requires-Python: >=3.9.0
Classifier: Development Status :: 5 - Production/Stable
Classifier: License :: OSI Approved :: MIT License
Classifier: Programming Language :: Python :: 3
Classifier: Programming Language :: Python :: 3.9
Classifier: Programming Language :: Python :: 3.10
Classifier: Programming Language :: Python :: 3.11
Classifier: Programming Language :: Python :: 3.12
Classifier: Topic :: Software Development
Classifier: Topic :: Software Development :: Quality Assurance
Classifier: Topic :: Software Development :: Testing
Requires-Dist: click (>=8)
Requires-Dist: colorclass (>=2.2.2)
Requires-Dist: pyyaml (>=6)
Project-URL: Repository, https://github.com/unconventionaldotdev/unbeheader
